design.sv
module decoder(out, i1, i2, c1, c2, c3);
  input c1, c2, c3;
  input wire [3:0] i1, i2;
  output reg [3:0] out;

  always @* begin
    if (c1 == 0 && c2 == 0 && c3 == 0) begin
      out = i1 + i2;
    end
    else if (c1 == 0 && c2 == 0 && c3 == 1) begin
      out = i1 - i2;
    end
    else if (c1 == 0 && c2 == 1 && c3 == 0) begin
      out = i1 * i2;
    end
    else if (c1 == 0 && c2 == 1 && c3 == 1) begin
      out = i1 / i2;
    end
    else if (c1 == 1 && c2 == 0 && c3 == 0) begin
      out = i1 & i2;
    end
    else if (c1 == 1 && c2 == 0 && c3 == 1) begin
      out = i1 | i2;  
    end
    else if (c1 == 1 && c2 == 1 && c3 == 0) begin
      out = i1 ^ i2;
    end
    else if (c1 == 1 && c2 == 1 && c3 == 1) begin
      out = ~i1;
    end
  end
endmodule

testbench.sv
`include "design.sv"

module tb_decoder;
reg c1 , c2, c3;
reg [3:0] i1, i2;
  wire [3:0] out;
  
  decoder test(out, i1, i2, c1, c2, c3);
  
  initial begin
    $dumpfile("dump.vcd");
    $dumpvars(1, tb_decoder);
    
    //test1 Addition
    c1 = 1'b0;
    c2 = 1'b0;
    c3 = 1'b0;
    
    i1 = 4'b0011;
    i2 = 4'b0011;
    
    #10 $display("c1 = %b, c2 = %b, c3 = %b, i1 = %b, i2 = %b, out = %b", c1, c2, c3, i1, i2, out);
    
    //test2 Subtraction
    c1 = 1'b0;
    c2 = 1'b0;
    c3 = 1'b1;
    
    i1 = 4'b0011;
    i2 = 4'b0011;
    
    #10 $display("c1 = %b, c2 = %b, c3 = %b, i1 = %b, i2 = %b, out = %b", c1, c2, c3, i1, i2, out);
    
    //test3 Multiplication
    c1 = 1'b0;
    c2 = 1'b1;
    c3 = 1'b0;
    
    i1 = 4'b0011;
    i2 = 4'b0011;
    
    #10 $display("c1 = %b, c2 = %b, c3 = %b, i1 = %b, i2 = %b, out = %b", c1, c2, c3, i1, i2, out);
    
    //test3 Division
    c1 = 1'b0;
    c2 = 1'b1;
    c3 = 1'b1;
    
    i1 = 4'b0011;
    i2 = 4'b0011;
    
    #10 $display("c1 = %b, c2 = %b, c3 = %b, i1 = %b, i2 = %b, out = %b", c1, c2, c3, i1, i2, out);
    
    //BitAND
    c1 = 1'b1;
    c2 = 1'b0;
    c3 = 1'b0;
    
    i1 = 4'b0011;
    i2 = 4'b0011;
    
    #10 $display("c1 = %b, c2 = %b, c3 = %b, i1 = %b, i2 = %b, out = %b", c1, c2, c3, i1, i2, out);
    
    //BitOR
    c1 = 1'b1;
    c2 = 1'b0;
    c3 = 1'b1;
    
    i1 = 4'b0011;
    i2 = 4'b0011;
    
    #10 $display("c1 = %b, c2 = %b, c3 = %b, i1 = %b, i2 = %b, out = %b", c1, c2, c3, i1, i2, out);
    
    //BitXOR
    c1 = 1'b1;
    c2 = 1'b1;
    c3 = 1'b0;
    
    i1 = 4'b0011;
    i2 = 4'b0011;
    
    #10 $display("c1 = %b, c2 = %b, c3 = %b, i1 = %b, i2 = %b, out = %b", c1, c2, c3, i1, i2, out);
    
    //BitNOT
    c1 = 1'b1;
    c2 = 1'b1;
    c3 = 1'b1;
    
    i1 = 4'b0011;
    
    #10 $display("c1 = %b, c2 = %b, c3 = %b, i1 = %b, i2 = %b, out = %b", c1, c2, c3, i1, i2, out);

  end
 

endmodule

dump.vcd
$date
	Wed Nov 29 01:52:49 2023
$end
$version
	Icarus Verilog
$end
$timescale
	1s
$end
$scope module tb_decoder $end
$var wire 4 ! out [3:0] $end
$var reg 1 " c1 $end
$var reg 1 # c2 $end
$var reg 1 $ c3 $end
$var reg 4 % i1 [3:0] $end
$var reg 4 & i2 [3:0] $end
$upscope $end
$enddefinitions $end
$comment Show the parameter values. $end
$dumpall
$end
#0
$dumpvars
b11 &
b11 %
0$
0#
0"
b110 !
$end
#10
b0 !
1$
#20
b1001 !
0$
1#
#30
b1 !
1$
#40
b11 !
0$
0#
1"
#50
1$
#60
b0 !
0$
1#
#70
b1100 !
1$
